classy_config/__init__.py
classy_config/_util.py
classy_config/config.py
classy_config/loader/__init__.py
classy_config/loader/auto_loader.py
classy_config/loader/env_loader.py
classy_config/loader/json_loader.py
classy_config/loader/loader.py
classy_config/loader/toml_loader.py
classy_config-0.7.1.dist-info/METADATA
classy_config-0.7.1.dist-info/WHEEL
classy_config-0.7.1.dist-info/licenses/LICENSE
classy_config-0.7.1.dist-info/RECORD
