Metadata-Version: 2.4
Name: classy_config
Version: 0.7.1
Summary: ClassyConfig is a Python3 package aiming to remove the need for a config.py or settings.py file.
License: MIT
License-File: LICENSE
Author: GDWR
Author-email: gregory.dwr@gmail.com
Requires-Python: >=3.10,<4.0
Classifier: License :: OSI Approved :: MIT License
Classifier: Programming Language :: Python :: 3
Classifier: Programming Language :: Python :: 3.10
Classifier: Programming Language :: Python :: 3.11
Classifier: Programming Language :: Python :: 3.12
Classifier: Programming Language :: Python :: 3.13
Classifier: Programming Language :: Python :: 3.14
Requires-Dist: pydantic (>=2.0.0,<3.0.0)
Requires-Dist: python-dotenv (>=1.0.0,<2.0.0)
Requires-Dist: tomli (>=2.0.0,<3.0.0)
Project-URL: Repository, https://github.com/GDWR/classy-config
